reefbuilder_segmentation/__init__.py
reefbuilder_segmentation/checks/__init__.py
reefbuilder_segmentation/checks/images.py
reefbuilder_segmentation/checks/labels.py
reefbuilder_segmentation/config.py
reefbuilder_segmentation/logging_config.json
reefbuilder_segmentation/modelling/__init__.py
reefbuilder_segmentation/modelling/base.py
reefbuilder_segmentation/preprocess/__init__.py
reefbuilder_segmentation/preprocess/dataset.py
reefbuilder_segmentation/utils/__init__.py
reefbuilder_segmentation/utils/checks/__init__.py
reefbuilder_segmentation/utils/checks/image_checks.py
reefbuilder_segmentation/utils/checks/label_checks.py
reefbuilder_segmentation/utils/general.py
reefbuilder_segmentation/utils/modelling/__init__.py
reefbuilder_segmentation/utils/modelling/yolo.py
reefbuilder_segmentation/utils/preprocessor/__init__.py
reefbuilder_segmentation/utils/preprocessor/dataset.py
reefbuilder_segmentation/utils/preprocessor/paths.py
reefbuilder_segmentation/utils/test_utils.py
reefbuilder_segmentation/utils/visualisation_utils.py
reefbuilder_segmentation-1.0.0.dist-info/LICENSE
reefbuilder_segmentation-1.0.0.dist-info/METADATA
reefbuilder_segmentation-1.0.0.dist-info/WHEEL
reefbuilder_segmentation-1.0.0.dist-info/RECORD
